carkov/__init__.py
carkov/__main__.py
carkov/abstracts.py
carkov/chain.py
carkov/filters.py
carkov/pydumper.py
carkov/serializer.py
carkov/utils.py
carkov/analyze/__init__.py
carkov/analyze/abstract.py
carkov/analyze/english.py
carkov/analyze/words.py
carkov-0.1.2.dist-info/LICENSE
carkov-0.1.2.dist-info/METADATA
carkov-0.1.2.dist-info/WHEEL
carkov-0.1.2.dist-info/entry_points.txt
carkov-0.1.2.dist-info/top_level.txt
carkov-0.1.2.dist-info/zip-safe
carkov-0.1.2.dist-info/RECORD
